MANIFEST.in
README.rst
setup.py
zcbot_crawl_sdk/__init__.py
zcbot_crawl_sdk.egg-info/PKG-INFO
zcbot_crawl_sdk.egg-info/SOURCES.txt
zcbot_crawl_sdk.egg-info/dependency_links.txt
zcbot_crawl_sdk.egg-info/requires.txt
zcbot_crawl_sdk.egg-info/top_level.txt
zcbot_crawl_sdk/receive/__init__.py
zcbot_crawl_sdk/receive/exceptions.py
zcbot_crawl_sdk/receive/model.py
zcbot_crawl_sdk/receive/processor.py
zcbot_crawl_sdk/receive/rabbit_keys.py
zcbot_crawl_sdk/receive/receiver.py
zcbot_crawl_sdk/util/__init__.py
zcbot_crawl_sdk/util/decator.py
zcbot_crawl_sdk/util/time.py